Metadata-Version: 2.1
Name: ebyte-lora-e32-rpi
Version: 0.0.3
Summary: Ebyte E32 LoRa raspberrypi library device very cheap and very long range (from 3Km to 8Km). Arduino LoRa EBYTE E32 device library complete and tested with Arduino, esp8266, esp32, STM32 and Raspberry Pi Pico. sx1278/sx1276.
Home-page: https://github.com/xreef/EByte_LoRa_E32_raspberrypi_library
Author: Renzo Mischianti
Author-email: Renzo Mischianti <renzo@mischianti.org>
Maintainer: Renzo Mischianti
Maintainer-email: Renzo Mischianti <renzo@mischianti.org>
License: The MIT License (MIT)
Project-URL: homepage, https://www.mischianti.org
Project-URL: Documentation, https://www.mischianti.org/category/my-libraries/lora-e32-devices/
Project-URL: Documentazione, https://www.mischianti.org/it/category/le-mie-librerie/dispositivi-lora-e32/
Project-URL: Repository, https://github.com/xreef/EByte_LoRa_E32_python_raspberrypi_library
Project-URL: Bug Tracker, https://github.com/xreef/EByte_LoRa_E32_python_raspberrypi_library/issues
Project-URL: Examples, https://github.com/xreef/EByte_LoRa_E32_python_raspberrypi_library/tree/main/examples
Keywords: lora,e32,ebyte,raspberrypi,UART,EByte,sx1278,sx1276
Classifier: Development Status :: 5 - Production/Stable
Classifier: Programming Language :: Python :: 3
Classifier: License :: OSI Approved :: MIT License
Requires-Python: >=3.7
License-File: LICENSE.md
